dittoed/__init__.py
dittoed/cli.py
dittoed/installables/base.py
dittoed/installables/command.py
dittoed/installables/distro.py
dittoed/installables/link.py
dittoed/installables/node.py
dittoed/installables/python.py
dittoed/installables/rust.py
dittoed/installables/vcs.py
dittoed/main.py
dittoed/util/merge.py
dittoed/util/python_path.py
dittoed-0.4.0.dist-info/METADATA
dittoed-0.4.0.dist-info/WHEEL
dittoed-0.4.0.dist-info/entry_points.txt
dittoed-0.4.0.dist-info/RECORD
