Metadata-Version: 2.1
Name: dittoed
Version: 0.4.0
Summary: A tool to help bootstrap your dev environment.
License: MPL-2.0
Author: Andrew Halberstadt
Author-email: ahal@pm.me
Requires-Python: >=3.10,<4.0
Classifier: License :: OSI Approved
Classifier: Programming Language :: Python :: 3
Classifier: Programming Language :: Python :: 3.10
Classifier: Programming Language :: Python :: 3.11
Classifier: Programming Language :: Python :: 3.12
Requires-Dist: tomli (>=1.2.2,<2.0.0)
